{
    "match_savestate_opponent":"",
    "match_savestate_player":"",
    "savestate_setup":1,
    "controllers":["player","unblockables"],
    "setup":1,
    "savestate_player":"",
    "savestate_opponent":"",
    "followups":{
      "oro":{
        "oro":[[false,false,false]],
        "yang":[[false,false,false]],
        "alex":[[false,false,false]],
        "elena":[[false,false,false]],
        "twelve":[[false,false,false]],
        "ibuki":[[false,false,false]],
        "shingouki":[[false,false,false]],
        "gill":[[false,false,false]],
        "hugo":[[false,false,false]],
        "q":[[false,false,false]],
        "dudley":[[false,false,false]],
        "remy":[[false,false,false]],
        "chunli":[[false,false,false]],
        "sean":[[false,false,false]],
        "makoto":[[false,false,false]],
        "necro":[[false,false,false]],
        "ryu":[[false,false,false]],
        "gouki":[[false,false,false]],
        "ken":[[false,false,false]],
        "urien":[[false,false,false]],
        "yun":[[false,false,false]]
      },
      "urien":{
        "oro":[[false,false,false,false],[false]],
        "yang":[[false,false,false,false],[false,false,false],[false]],
        "alex":[[false,false,false,false],[false,false,false],[false]],
        "elena":[[false,false,false],[false]],
        "twelve":[[false,false,false,false],[false,false,false],[false]],
        "ibuki":[[false,false,false,false],[false,false,false]],
        "shingouki":[[false,false,false],[false,false,false,false],[false,false,false],[false]],
        "gill":[[false,false,false],[false,false,false,false],[false,false,false],[false]],
        "hugo":[[false,false,false,false],[false,false,false],[false]],
        "q":[[false,false,false,false],[false,false,false],[false]],
        "dudley":[[false,false,false,false],[false,false,false],[false]],
        "remy":[[false,false,false,false],[false,false,false],[false]],
        "chunli":[[false,false,false],[false,false,false,false],[false,false,false],[false]],
        "sean":[[false,false,false],[false,false,false,false],[false,false,false],[false]],
        "makoto":[[false,false,false],[false,false,false,false],[false,false,false],[false]],
        "necro":[[false,false,false,false],[false,false,false],[false]],
        "ryu":[[false,false,false],[false,false,false,false],[false,false,false],[false]],
        "gouki":[[false,false,false],[false,false,false,false],[false,false,false],[false]],
        "ken":[[false,false,false],[false,false,false,false],[false,false,false],[false]],
        "urien":[[false,false,false],[false,false,false,false],[false,false,false],[false]],
        "yun":[[false,false,false,false],[false,false,false],[false]]
      }
    },
    "opponent":1
  }
